README.md
setup.py
mytools/__init__.py
mytools/binning.py
mytools/index_transits.py
mytools/lightcurve_tools.py
mytools/pandas_tsa.py
mytools/phase_fold.py
mytools/plot_utils.py
mytools/running_median.py
mytools/set_nan.py
mytools/utils.py
mytools.egg-info/PKG-INFO
mytools.egg-info/SOURCES.txt
mytools.egg-info/dependency_links.txt
mytools.egg-info/requires.txt
mytools.egg-info/top_level.txt