Metadata-Version: 1.1
Name: mytools
Version: 1.1.2
Summary: Set of tools for photometric time series data and plotting
Home-page: https://github.com/MNGuenther/mytools
Author: Maximilian N. Guenther
Author-email: mg719@cam.ac.uk
License: UNKNOWN
Download-URL: https://github.com/MNGuenther/mytools/releases
Platform: UNKNOWN
